{
  "job_id": 1303,
  "variant": "P2",
  "reasoning": "The experience and skills listed in the resume have been cross-referenced with the job description for the IT Support/Technician Intern position at ETech 7. The resume includes relevant experiences such as the IT Support Intern role at the Mayor's Office of Information Services, which aligns with the job's focus on end-user support and troubleshooting. The skills in the resume, including Active Directory, Windows operating systems, and helpdesk support, directly match the requirements outlined in the job description. Unsupported claims, such as advanced AWS architecture design, have been removed to ensure accuracy.",
  "resume_markdown": "# Darwhin Gomez\n\n**Email:** Darwhin88@gmail.com  \n**Phone:** 929-305-7353  \n**Location:** New York City  \n**LinkedIn:** [LinkedIn](https://www.linkedin.com/in/darwhin)  \n**GitHub:** [GitHub](https://github.com/dw8888)  \n\n## Education\n**Bachelor of Technology \u2013 Computer Information Systems**  \nNew York City College of Technology (The City University of New York)  \nGPA: 3.78 | Expected Graduation: Jun 2024  \n\n## Experience\n### Volunteer IT Support and Development Intern  \n**Mayor\u2019s Office of Information Services**  \nNew York, NY  \nFeb 2024 \u2013 Current  \n- Provide support to the helpdesk, development, and server teams.  \n- Assist in providing white glove service to end users, including VIPs.  \n- Participate in a project to restore over 400 out-of-commission devices through hardware and software updates.  \n- Deploy scripts remotely to support, maintain, and troubleshoot devices and infrastructure.  \n- Communicate with team members at all levels to facilitate tasks and project completions.  \n- Leverage tools like ServiceDesk, Active Directory, Python, and Batch scripts to execute required tasks.  \n\n### IT Instructor Assistant  \n**RF CUNY & Generation USA**  \nNew York, NY  \nFeb 2022 - Aug 2023  \n- Taught 36 lessons to over 200 learners in various IT concepts and technologies.  \n- Planned and led workshops in Scripting in Linux and PowerShell.  \n- Created a technical lab and documented solutions for configuring and implementing a RAID solution in Windows 10.  \n- Achieved a 96% cohort graduation rate.  \n- Collaborated with team members through ZOOM, ASANA, SLACK, and Google Suite.  \n\n## Skills\n- **Operating Systems:** Windows, Linux  \n- **Tools:** Microsoft Office, ServiceNow, Active Directory  \n- **Programming Languages:** Python  \n- **Soft Skills:** Excellent verbal and written communication, collaboration, customer service  \n\n## Certifications\n- Google Cybersecurity Certificate  \n- Google Information Support Certificate  \n\n## Projects\n- Developed a technical lab for configuring and implementing IT solutions, enhancing student learning and engagement.",
  "artifact_id": 224
}